{
	"info": {
		"_postman_id": "f01f7fd1-94a1-42d0-8ec1-55b937c86c42",
		"name": "TaskEvalPro API Without Auth",
		"schema": "https://schema.getpostman.com/json/collection/v2.1.0/collection.json",
		"_exporter_id": "9456682"
	},
	"item": [
		{
			"name": "Get All Users",
			"request": {
				"method": "GET",
				"header": [],
				"url": {
					"raw": "http://localhost:5100/api/usuarios",
					"protocol": "http",
					"host": [
						"localhost"
					],
					"port": "5100",
					"path": [
						"api",
						"usuarios"
					]
				}
			},
			"response": []
		},
		{
			"name": "Get User by ID",
			"request": {
				"method": "GET",
				"header": [],
				"url": {
					"raw": "http://localhost:5100/api/usuario/1",
					"protocol": "http",
					"host": [
						"localhost"
					],
					"port": "5100",
					"path": [
						"api",
						"usuario",
						"1"
					]
				}
			},
			"response": []
		},
		{
			"name": "Create User",
			"request": {
				"method": "POST",
				"header": [
					{
						"key": "Content-Type",
						"value": "application/json"
					}
				],
				"body": {
					"mode": "raw",
					"raw": "{\n\t\"nome_usuario\": \"example_user\",\n\t\"email\": \"example@example.com\",\n\t\"papel\": \"user_role\"\n}"
				},
				"url": {
					"raw": "http://localhost:5100/api/usuarios",
					"protocol": "http",
					"host": [
						"localhost"
					],
					"port": "5100",
					"path": [
						"api",
						"usuarios"
					]
				}
			},
			"response": []
		},
		{
			"name": "Update User",
			"request": {
				"method": "PUT",
				"header": [
					{
						"key": "Content-Type",
						"value": "application/json"
					}
				],
				"body": {
					"mode": "raw",
					"raw": "{\n\t\"nome_usuario\": \"updated_user\",\n\t\"email\": \"updated@example.com\",\n\t\"papel\": \"updated_role\"\n}"
				},
				"url": {
					"raw": "http://localhost:5100/api/usuarios/1",
					"protocol": "http",
					"host": [
						"localhost"
					],
					"port": "5100",
					"path": [
						"api",
						"usuarios",
						"1"
					]
				}
			},
			"response": []
		},
		{
			"name": "Delete User",
			"request": {
				"method": "DELETE",
				"header": [],
				"url": {
					"raw": "http://localhost:5100/api/usuarios/1",
					"protocol": "http",
					"host": [
						"localhost"
					],
					"port": "5100",
					"path": [
						"api",
						"usuarios",
						"1"
					]
				}
			},
			"response": []
		},
		{
			"name": "Get All Tasks",
			"request": {
				"method": "GET",
				"header": [],
				"url": {
					"raw": "http://localhost:5100/api/tarefas",
					"protocol": "http",
					"host": [
						"localhost"
					],
					"port": "5100",
					"path": [
						"api",
						"tarefas"
					]
				}
			},
			"response": []
		},
		{
			"name": "Get Task by ID",
			"request": {
				"method": "GET",
				"header": [],
				"url": {
					"raw": "http://localhost:5100/api/tarefa/1",
					"protocol": "http",
					"host": [
						"localhost"
					],
					"port": "5100",
					"path": [
						"api",
						"tarefa",
						"1"
					]
				}
			},
			"response": []
		},
		{
			"name": "Create Task",
			"request": {
				"method": "POST",
				"header": [
					{
						"key": "Content-Type",
						"value": "application/json"
					}
				],
				"body": {
					"mode": "raw",
					"raw": "{\n\t\"titulo\": \"Ir ao médico\",\n\t\"descricao\": \"Ir ao médico\",\n\t\"prioridade\": 1,\n\t\"prazo\": \"2024-03-30\",\n\t\"status\": false,\n\t\"id_criador\": 3,\n\t\"id_responsavel\": 3\n}"
				},
				"url": {
					"raw": "http://localhost:5100/api/tarefas",
					"protocol": "http",
					"host": [
						"localhost"
					],
					"port": "5100",
					"path": [
						"api",
						"tarefas"
					]
				}
			},
			"response": []
		},
		{
			"name": "Update Task",
			"request": {
				"method": "PUT",
				"header": [
					{
						"key": "Content-Type",
						"value": "application/json"
					}
				],
				"body": {
					"mode": "raw",
					"raw": "{\n\t\"titulo\": \"Updated Task Title\",\n\t\"descricao\": \"Updated description here\",\n\t\"prioridade\": 2,\n\t\"prazo\": \"2025-01-01\",\n\t\"status\": true,\n\t\"id_responsavel\": 2\n}"
				},
				"url": {
					"raw": "http://localhost:5100/api/tarefas/1",
					"protocol": "http",
					"host": [
						"localhost"
					],
					"port": "5100",
					"path": [
						"api",
						"tarefas",
						"1"
					]
				}
			},
			"response": []
		},
		{
			"name": "Delete Task",
			"request": {
				"method": "DELETE",
				"header": [],
				"url": {
					"raw": "http://localhost:5100/api/tarefas/1",
					"protocol": "http",
					"host": [
						"localhost"
					],
					"port": "5100",
					"path": [
						"api",
						"tarefas",
						"1"
					]
				}
			},
			"response": []
		},
		{
			"name": "Get All Evaluations",
			"request": {
				"method": "GET",
				"header": [],
				"url": {
					"raw": "http://localhost:5100/api/avaliacoes",
					"protocol": "http",
					"host": [
						"localhost"
					],
					"port": "5100",
					"path": [
						"api",
						"avaliacoes"
					]
				}
			},
			"response": []
		},
		{
			"name": "Get Evaluation by ID",
			"request": {
				"method": "GET",
				"header": [],
				"url": {
					"raw": "http://localhost:5100/api/avaliacao/1",
					"protocol": "http",
					"host": [
						"localhost"
					],
					"port": "5100",
					"path": [
						"api",
						"avaliacao",
						"1"
					]
				}
			},
			"response": []
		},
		{
			"name": "Create Evaluation",
			"request": {
				"method": "POST",
				"header": [
					{
						"key": "Content-Type",
						"value": "application/json"
					}
				],
				"body": {
					"mode": "raw",
					"raw": "{\n\t\"criterios_avaliacao\": \"Criterios \",\n\t\"pontuacao\": 10,\n\t\"comentarios\": \"Bom trabalho! Excelente\",\n\t\"id_tarefa_avaliada\": 1,\n\t\"id_avaliador\": 1,\n\t\"data_avaliacao\": \"2024-01-01\"\n}"
				},
				"url": {
					"raw": "http://localhost:5100/api/avaliacoes",
					"protocol": "http",
					"host": [
						"localhost"
					],
					"port": "5100",
					"path": [
						"api",
						"avaliacoes"
					]
				}
			},
			"response": []
		},
		{
			"name": "Update Evaluation",
			"request": {
				"method": "PUT",
				"header": [
					{
						"key": "Content-Type",
						"value": "application/json"
					}
				],
				"body": {
					"mode": "raw",
					"raw": "{\n\t\"criterios_avaliacao\": \"Criterios 3\",\n\t\"pontuacao\": 7.5,\n\t\"comentarios\": \"Foi bom, mas há algumas possibilidades de melhoria\",\n\t\"data_avaliacao\": \"2024-02-01\"\n}"
				},
				"url": {
					"raw": "http://localhost:5100/api/avaliacoes/3",
					"protocol": "http",
					"host": [
						"localhost"
					],
					"port": "5100",
					"path": [
						"api",
						"avaliacoes",
						"3"
					]
				}
			},
			"response": []
		},
		{
			"name": "Delete Evaluation",
			"request": {
				"method": "DELETE",
				"header": [],
				"url": {
					"raw": "http://localhost:5100/api/avaliacoes/1",
					"protocol": "http",
					"host": [
						"localhost"
					],
					"port": "5100",
					"path": [
						"api",
						"avaliacoes",
						"1"
					]
				}
			},
			"response": []
		}
	]
}